flightdeck/__init__.py
flightdeck/apikey.py
flightdeck/background.jpg
flightdeck/file_path.py
flightdeck/main.py
flightdeck/pomodoro.py
flightdeck/vault.py
flightdeck/weather.py
flightdeck/files/__init__.py
flightdeck/files/handler.py
flightdeck/files/markdown.py
flightdeck/files/picture.py
flightdeck/timer/__init__.py
flightdeck-10.10.23.dist-info/METADATA
flightdeck-10.10.23.dist-info/WHEEL
flightdeck-10.10.23.dist-info/entry_points.txt
flightdeck-10.10.23.dist-info/top_level.txt
flightdeck-10.10.23.dist-info/RECORD
